DataScience/BigData.py
DataScience/DeepLearning.py
DataScience/MachineLearning.py
DataScience/__init__.py
Minus1By12-1.0.4.dist-info/LICENSE
Minus1By12-1.0.4.dist-info/METADATA
Minus1By12-1.0.4.dist-info/WHEEL
Minus1By12-1.0.4.dist-info/top_level.txt
Minus1By12-1.0.4.dist-info/RECORD
