Metadata-Version: 2.1
Name: Minus1By12
Version: 1.0.4
Summary: BigData, CoreML & DeepLearning Assistance Library
Home-page: https://github.com/MinusOneByTwelve/Minus1By12
Author: MinusOneByTwelve Solutions LLP
Author-email: Contact@Minus1By12.com
License: UNKNOWN
Download-URL: https://github.com/MinusOneByTwelve/Minus1By12/archive/1.0.4.tar.gz
Platform: UNKNOWN
Classifier: Programming Language :: Python :: 3
Classifier: License :: OSI Approved :: MIT License
Classifier: Operating System :: OS Independent
